Metadata-Version: 2.1
Name: fpqr
Version: 0.0.2
Summary: A quantile based dimension reduction technique for regression
Home-page: https://github.com/alvaromc317/fpqr
Author: Alvaro Mendez Civieta
Author-email: alvaro.mendez@uc3m.es
License: GNU General Public License
Download-URL: https://github.com/alvaromc317/fpqr/archive/refs/tags/v_0_0_2.tar.gz
Keywords: partial-least-squares,quantile-regression,dimension-reduction,outliers,robust
Platform: UNKNOWN
Requires-Python: >=3.5
License-File: LICENSE
